<annotation>
	<folder>plates</folder>
	<filename>IMG-20180108-WA0079.jpg</filename>
	<path>/home/idiot/Dataset/plates/IMG-20180108-WA0079.jpg</path>
	<source>
		<database>Unknown</database>
	</source>
	<size>
		<width>1040</width>
		<height>585</height>
		<depth>3</depth>
	</size>
	<segmented>0</segmented>
	<object>
		<name>plate</name>
		<pose>Unspecified</pose>
		<truncated>0</truncated>
		<difficult>0</difficult>
		<bndbox>
			<xmin>804</xmin>
			<ymin>290</ymin>
			<xmax>879</xmax>
			<ymax>328</ymax>
		</bndbox>
	</object>
	<object>
		<name>plate</name>
		<pose>Unspecified</pose>
		<truncated>0</truncated>
		<difficult>0</difficult>
		<bndbox>
			<xmin>597</xmin>
			<ymin>290</ymin>
			<xmax>666</xmax>
			<ymax>328</ymax>
		</bndbox>
	</object>
	<object>
		<name>plate</name>
		<pose>Unspecified</pose>
		<truncated>0</truncated>
		<difficult>0</difficult>
		<bndbox>
			<xmin>361</xmin>
			<ymin>274</ymin>
			<xmax>426</xmax>
			<ymax>297</ymax>
		</bndbox>
	</object>
</annotation>
